LICENSE.txt
MANIFEST.in
README.rst
setup.cfg
setup.py
data/data_file
opentest/__init__.py
opentest/grpc_utils.py
opentest/mode_utils.py
opentest/netconf_utils.py
opentest/nso_utils.py
opentest/rest_utils.py
opentest.egg-info/PKG-INFO
opentest.egg-info/SOURCES.txt
opentest.egg-info/dependency_links.txt
opentest.egg-info/entry_points.txt
opentest.egg-info/requires.txt
opentest.egg-info/top_level.txt