Metadata-Version: 1.1
Name: opentest
Version: 0.9
Summary: open test Project
Home-page: http://gitlab.cisco.com/vinapai/opentest.git
Author: The Cisco Python Packaging Authority
Author-email: vinapai@cisco.com
License: MIT
Keywords: sample setuptools development
Platform: UNKNOWN
Classifier: Development Status :: 3 - Alpha
Classifier: Intended Audience :: Developers
Classifier: Topic :: Software Development :: Build Tools
Classifier: License :: OSI Approved :: MIT License
Classifier: Programming Language :: Python :: 3.4
